columnPrinter.py
columnPrinter-1.0.dist-info/WHEEL
columnPrinter-1.0.dist-info/METADATA
columnPrinter-1.0.dist-info/RECORD
