Metadata-Version: 2.1
Name: columnPrinter
Version: 1.0
Summary: ColPrint
Home-page: https://github.com/dguis/columnPrinter
License: UNKNOWN
Author: Dallin Guisti
Author-email: support@d-multi.com
Classifier: License :: OSI Approved :: MIT License
